napari_3dtimereg/Utils.py
napari_3dtimereg/__init__.py
napari_3dtimereg/movieRegistration.py
napari_3dtimereg/napari.yaml
napari_3dtimereg-0.0.11.dist-info/LICENSE
napari_3dtimereg-0.0.11.dist-info/METADATA
napari_3dtimereg-0.0.11.dist-info/WHEEL
napari_3dtimereg-0.0.11.dist-info/entry_points.txt
napari_3dtimereg-0.0.11.dist-info/top_level.txt
napari_3dtimereg-0.0.11.dist-info/RECORD
