Metadata-Version: 2.1
Name: napari-3dtimereg
Version: 0.0.11
Summary: Registration of 3D movies applied to all channels
Home-page: https://gitlab.pasteur.fr/gletort/napari-3dtimereg
Author: Gaëlle Letort
Author-email: gaelle.letort@pasteur.fr
License: BSD-3-Clause
Project-URL: Bug Tracker, https://gitlab.pasteur.fr/gletort/napari-3dtimereg/issues
Project-URL: Documentation, https://gitlab.pasteur.fr/gletort/napari-3dtimereg#README.md
Project-URL: Source Code, https://gitlab.pasteur.fr/gletort/napari-3dtimereg
Classifier: Framework :: napari
Classifier: Intended Audience :: Developers
Classifier: License :: OSI Approved :: BSD License
Classifier: Operating System :: OS Independent
Classifier: Programming Language :: Python
Classifier: Programming Language :: Python :: 3
Classifier: Programming Language :: Python :: 3 :: Only
Classifier: Programming Language :: Python :: 3.8
Classifier: Programming Language :: Python :: 3.9
Classifier: Programming Language :: Python :: 3.10
Classifier: Topic :: Scientific/Engineering :: Image Processing
Requires-Python: >=3.8
License-File: LICENSE
Requires-Dist: numpy
Requires-Dist: napari
Requires-Dist: magicgui
Requires-Dist: qtpy
Requires-Dist: tifffile
Requires-Dist: imaris_ims_file_reader
Requires-Dist: czifile
Requires-Dist: itk==5.3.0
Requires-Dist: itk-registration
Requires-Dist: itk-elastix
Requires-Dist: pydantic<=1.10.14
